{
    "savedObjects": [
        {
            "saveID": "enemy position 19",
            "playerPosition": {
                "x": 0.0,
                "y": 0.0,
                "z": 0.0
            },
            "enemyStartTimer": 0.0,
            "enemySpeed": 3.0,
            "enemyPosition": {
                "x": -11.5,
                "y": 0.03283262252807617,
                "z": 0.0
            }
        },
        {
            "saveID": "enemy position 18",
            "playerPosition": {
                "x": 0.0,
                "y": 0.0,
                "z": 0.0
            },
            "enemyStartTimer": 0.0,
            "enemySpeed": 5.0,
            "enemyPosition": {
                "x": -11.5,
                "y": 1.0020110607147217,
                "z": 0.0
            }
        },
        {
            "saveID": "enemy position 17",
            "playerPosition": {
                "x": 0.0,
                "y": 0.0,
                "z": 0.0
            },
            "enemyStartTimer": 0.0,
            "enemySpeed": 7.0,
            "enemyPosition": {
                "x": -11.5,
                "y": 2.9976601600646974,
                "z": 0.0
            }
        },
        {
            "saveID": "enemy position 16",
            "playerPosition": {
                "x": 0.0,
                "y": 0.0,
                "z": 0.0
            },
            "enemyStartTimer": 0.0,
            "enemySpeed": 3.0,
            "enemyPosition": {
                "x": -11.5,
                "y": 2.3172452449798586,
                "z": 0.0
            }
        },
        {
            "saveID": "enemy position 15",
            "playerPosition": {
                "x": 0.0,
                "y": 0.0,
                "z": 0.0
            },
            "enemyStartTimer": 0.0,
            "enemySpeed": 3.0,
            "enemyPosition": {
                "x": -11.5,
                "y": 0.9136242866516113,
                "z": 0.0
            }
        },
        {
            "saveID": "enemy position 14",
            "playerPosition": {
                "x": 0.0,
                "y": 0.0,
                "z": 0.0
            },
            "enemyStartTimer": 0.0,
            "enemySpeed": 5.0,
            "enemyPosition": {
                "x": -11.5,
                "y": 2.5135459899902345,
                "z": 0.0
            }
        },
        {
            "saveID": "enemy position 13",
            "playerPosition": {
                "x": 0.0,
                "y": 0.0,
                "z": 0.0
            },
            "enemyStartTimer": 0.0,
            "enemySpeed": 5.0,
            "enemyPosition": {
                "x": -11.5,
                "y": 1.3916652202606202,
                "z": 0.0
            }
        },
        {
            "saveID": "enemy position 12",
            "playerPosition": {
                "x": 0.0,
                "y": 0.0,
                "z": 0.0
            },
            "enemyStartTimer": 0.0,
            "enemySpeed": 3.0,
            "enemyPosition": {
                "x": -11.5,
                "y": 0.7056608200073242,
                "z": 0.0
            }
        },
        {
            "saveID": "enemy position 11",
            "playerPosition": {
                "x": 0.0,
                "y": 0.0,
                "z": 0.0
            },
            "enemyStartTimer": 0.0,
            "enemySpeed": 5.0,
            "enemyPosition": {
                "x": -11.5,
                "y": 1.4044888019561768,
                "z": 0.0
            }
        },
        {
            "saveID": "enemy position 10",
            "playerPosition": {
                "x": 0.0,
                "y": 0.0,
                "z": 0.0
            },
            "enemyStartTimer": 0.0,
            "enemySpeed": 3.0,
            "enemyPosition": {
                "x": -11.5,
                "y": 3.073678970336914,
                "z": 0.0
            }
        },
        {
            "saveID": "enemy position 9",
            "playerPosition": {
                "x": 0.0,
                "y": 0.0,
                "z": 0.0
            },
            "enemyStartTimer": 0.0,
            "enemySpeed": 5.0,
            "enemyPosition": {
                "x": -11.5,
                "y": 0.20883560180664063,
                "z": 0.0
            }
        },
        {
            "saveID": "enemy position 8",
            "playerPosition": {
                "x": 0.0,
                "y": 0.0,
                "z": 0.0
            },
            "enemyStartTimer": 0.0,
            "enemySpeed": 3.0,
            "enemyPosition": {
                "x": -11.5,
                "y": 2.993107795715332,
                "z": 0.0
            }
        },
        {
            "saveID": "enemy position 7",
            "playerPosition": {
                "x": 0.0,
                "y": 0.0,
                "z": 0.0
            },
            "enemyStartTimer": 0.0,
            "enemySpeed": 7.0,
            "enemyPosition": {
                "x": -11.5,
                "y": 3.675319194793701,
                "z": 0.0
            }
        },
        {
            "saveID": "enemy position 6",
            "playerPosition": {
                "x": 0.0,
                "y": 0.0,
                "z": 0.0
            },
            "enemyStartTimer": 0.0,
            "enemySpeed": 5.0,
            "enemyPosition": {
                "x": -11.5,
                "y": 2.2365214824676515,
                "z": 0.0
            }
        },
        {
            "saveID": "enemy position 5",
            "playerPosition": {
                "x": 0.0,
                "y": 0.0,
                "z": 0.0
            },
            "enemyStartTimer": 0.0,
            "enemySpeed": 3.0,
            "enemyPosition": {
                "x": -11.5,
                "y": 3.2398500442504885,
                "z": 0.0
            }
        },
        {
            "saveID": "enemy position 4",
            "playerPosition": {
                "x": 0.0,
                "y": 0.0,
                "z": 0.0
            },
            "enemyStartTimer": 0.0,
            "enemySpeed": 5.0,
            "enemyPosition": {
                "x": -11.5,
                "y": 2.287872552871704,
                "z": 0.0
            }
        },
        {
            "saveID": "enemy position 3",
            "playerPosition": {
                "x": 0.0,
                "y": 0.0,
                "z": 0.0
            },
            "enemyStartTimer": 0.0,
            "enemySpeed": 7.0,
            "enemyPosition": {
                "x": -11.5,
                "y": 2.724623203277588,
                "z": 0.0
            }
        },
        {
            "saveID": "enemy position 2",
            "playerPosition": {
                "x": 0.0,
                "y": 0.0,
                "z": 0.0
            },
            "enemyStartTimer": 0.0,
            "enemySpeed": 5.0,
            "enemyPosition": {
                "x": 1.400007724761963,
                "y": 1.445202112197876,
                "z": 0.0
            }
        },
        {
            "saveID": "enemy position 1",
            "playerPosition": {
                "x": 0.0,
                "y": 0.0,
                "z": 0.0
            },
            "enemyStartTimer": 0.0,
            "enemySpeed": 3.0,
            "enemyPosition": {
                "x": -9.759987831115723,
                "y": 0.059847354888916019,
                "z": 0.0
            }
        },
        {
            "saveID": "enemy position 0",
            "playerPosition": {
                "x": 0.0,
                "y": 0.0,
                "z": 0.0
            },
            "enemyStartTimer": 0.0,
            "enemySpeed": 5.0,
            "enemyPosition": {
                "x": -3.5999913215637209,
                "y": 1.2108910083770753,
                "z": 0.0
            }
        },
        {
            "saveID": "player",
            "playerPosition": {
                "x": -1.48874032497406,
                "y": -3.0,
                "z": 0.0
            },
            "enemyStartTimer": 0.0,
            "enemySpeed": 0.0,
            "enemyPosition": {
                "x": 0.0,
                "y": 0.0,
                "z": 0.0
            }
        }
    ]
}